MANIFEST.in
README.rst
requirements.txt
setup.py
relish/__init__.py
relish.egg-info/PKG-INFO
relish.egg-info/SOURCES.txt
relish.egg-info/dependency_links.txt
relish.egg-info/top_level.txt
relish/decorators/__init__.py
relish/decorators/auth.py
relish/decorators/generic.py
relish/helpers/__init__.py
relish/helpers/request.py
relish/helpers/show.py
relish/helpers/site.py
relish/helpers/upload.py
relish/models/__init__.py
relish/views/__init__.py
relish/views/messages.py