Metadata-Version: 1.1
Name: relish
Version: 0.1.0
Summary: Useful code snippets for django
Home-page: https://github.com/st4lk/django-relish
Author: st4lk
Author-email: alexevseev@gmail.com
License: BSD License
Keywords: django,snippet,relish
Platform: Any
Classifier: Environment :: Web Environment
Classifier: Framework :: Django
Classifier: Intended Audience :: Developers
Classifier: License :: OSI Approved :: BSD License
Classifier: Operating System :: OS Independent
Classifier: Programming Language :: Python
Classifier: Topic :: Utilities
